django_validation/__init__.py
django_validation/custom_validations.py
django_validation/model_validations.py
custom_django_validation-0.0.1.dist-info/METADATA
custom_django_validation-0.0.1.dist-info/WHEEL
custom_django_validation-0.0.1.dist-info/top_level.txt
custom_django_validation-0.0.1.dist-info/RECORD
