Metadata-Version: 2.1
Name: custom-django-validation
Version: 0.0.1
Summary: django model and base validations
Author: Shaghayegh Ghorbanpoor
Author-email: ghorbanpoor.shaghayegh@gmail.com
Classifier: Programming Language :: Python :: 3
Classifier: License :: OSI Approved :: MIT License
Classifier: Operating System :: OS Independent
Requires-Python: >=3.8
